MANIFEST.in
README.md
requirements.txt
setup.py
version.txt
gplist/__init__.py
gplist/__main__.py
gplist/mobileprovision.py
gplist/plist.py
gplist.egg-info/PKG-INFO
gplist.egg-info/SOURCES.txt
gplist.egg-info/dependency_links.txt
gplist.egg-info/requires.txt
gplist.egg-info/top_level.txt
tests/requirements.txt