Metadata-Version: 2.1
Name: gplist
Version: 0.0.15
Summary: pure python plist manipulator
Home-page: https://github.com/guyingzhao/gplist.git
Author: guyingzhao
Author-email: 572488191@qq.com
License: MIT
Platform: UNKNOWN
